mcp_yx_weather/__init__.py
mcp_yx_weather/weather.py
mcp_yx_weather-0.1.3.dist-info/METADATA
mcp_yx_weather-0.1.3.dist-info/WHEEL
mcp_yx_weather-0.1.3.dist-info/entry_points.txt
mcp_yx_weather-0.1.3.dist-info/RECORD
