Metadata-Version: 2.4
Name: mcp-yx-weather
Version: 0.1.3
Summary: Add your description here
Author-email: 御雪 <wb-spf530106@alibaba-inc.com>
Requires-Python: >=3.10
Requires-Dist: httpx>=0.28.1
Requires-Dist: mcp[cli]>=1.6.0
